<annotation>
	<folder>Ahmed 2</folder>
	<filename>151445-1566837183.-D24C34AA-9C5B-43D0-8313-C563E2B196EA.jpg</filename>
	<path>C:\Users\ahmed.nawaz\Desktop\Ahmed 2\151445-1566837183.-D24C34AA-9C5B-43D0-8313-C563E2B196EA.jpg</path>
	<source>
		<database>Unknown</database>
	</source>
	<size>
		<width>750</width>
		<height>1334</height>
		<depth>3</depth>
	</size>
	<segmented>0</segmented>
	<object>
		<name>doc</name>
		<pose>Unspecified</pose>
		<truncated>1</truncated>
		<difficult>0</difficult>
		<bndbox>
			<xmin>72</xmin>
			<ymin>269</ymin>
			<xmax>589</xmax>
			<ymax>1334</ymax>
		</bndbox>
	</object>
</annotation>
