<annotation>
	<folder>8 JAN</folder>
	<filename>30713d22-f4fa-1ff8-5282-12d358deb952.jpg</filename>
	<path>C:\Users\aqeel.ahmedjr\Desktop\8 JAN\30713d22-f4fa-1ff8-5282-12d358deb952.jpg</path>
	<source>
		<database>Unknown</database>
	</source>
	<size>
		<width>800</width>
		<height>600</height>
		<depth>3</depth>
	</size>
	<segmented>0</segmented>
	<object>
		<name>doc</name>
		<pose>Unspecified</pose>
		<truncated>0</truncated>
		<difficult>0</difficult>
		<bndbox>
			<xmin>189</xmin>
			<ymin>17</ymin>
			<xmax>701</xmax>
			<ymax>596</ymax>
		</bndbox>
	</object>
</annotation>
