<annotation>
	<folder>8 JAN</folder>
	<filename>4a7a8d86-0ba2-1847-2ae4-b7f859ed3362.jpg</filename>
	<path>C:\Users\aqeel.ahmedjr\Desktop\8 JAN\4a7a8d86-0ba2-1847-2ae4-b7f859ed3362.jpg</path>
	<source>
		<database>Unknown</database>
	</source>
	<size>
		<width>800</width>
		<height>600</height>
		<depth>3</depth>
	</size>
	<segmented>0</segmented>
	<object>
		<name>doc</name>
		<pose>Unspecified</pose>
		<truncated>0</truncated>
		<difficult>0</difficult>
		<bndbox>
			<xmin>5</xmin>
			<ymin>147</ymin>
			<xmax>762</xmax>
			<ymax>508</ymax>
		</bndbox>
	</object>
</annotation>
