<annotation>
	<folder>Ahmed 2</folder>
	<filename>5969-1567021406228-c7c515cf3b064529a8feae92670045a3.jpg</filename>
	<path>C:\Users\ahmed.nawaz\Desktop\Ahmed 2\5969-1567021406228-c7c515cf3b064529a8feae92670045a3.jpg</path>
	<source>
		<database>Unknown</database>
	</source>
	<size>
		<width>767</width>
		<height>1440</height>
		<depth>3</depth>
	</size>
	<segmented>0</segmented>
	<object>
		<name>doc</name>
		<pose>Unspecified</pose>
		<truncated>1</truncated>
		<difficult>0</difficult>
		<bndbox>
			<xmin>142</xmin>
			<ymin>78</ymin>
			<xmax>596</xmax>
			<ymax>1440</ymax>
		</bndbox>
	</object>
</annotation>
