<annotation>
	<folder>8 JAN</folder>
	<filename>8912ac6b-b71b-2045-95f1-2f00bf7a3be8.jpg</filename>
	<path>C:\Users\aqeel.ahmedjr\Desktop\8 JAN\8912ac6b-b71b-2045-95f1-2f00bf7a3be8.jpg</path>
	<source>
		<database>Unknown</database>
	</source>
	<size>
		<width>800</width>
		<height>600</height>
		<depth>3</depth>
	</size>
	<segmented>0</segmented>
	<object>
		<name>doc</name>
		<pose>Unspecified</pose>
		<truncated>0</truncated>
		<difficult>0</difficult>
		<bndbox>
			<xmin>8</xmin>
			<ymin>199</ymin>
			<xmax>752</xmax>
			<ymax>499</ymax>
		</bndbox>
	</object>
</annotation>
