<annotation>
	<folder>TTT</folder>
	<filename>ing (267).jpg</filename>
	<path>C:\Users\zaheer.ahmad\Desktop\TTT\ing (267).jpg</path>
	<source>
		<database>Unknown</database>
	</source>
	<size>
		<width>4224</width>
		<height>2376</height>
		<depth>3</depth>
	</size>
	<segmented>0</segmented>
	<object>
		<name>doc</name>
		<pose>Unspecified</pose>
		<truncated>0</truncated>
		<difficult>0</difficult>
		<bndbox>
			<xmin>839</xmin>
			<ymin>283</ymin>
			<xmax>3518</xmax>
			<ymax>2148</ymax>
		</bndbox>
	</object>
</annotation>
